geoapi/__init__.py
geoapi/app.py
geoapi/views/__init__.py
geoapi/views/api.py
geoapi-1.0.1.dist-info/METADATA
geoapi-1.0.1.dist-info/WHEEL
geoapi-1.0.1.dist-info/entry_points.txt
geoapi-1.0.1.dist-info/top_level.txt
geoapi-1.0.1.dist-info/RECORD
